{
  "metadata": {},
  "dashboardMetadata": {
    "name": "AWS CodeBuild",
    "sharingDetails": {
      "linkShared": true,
      "published": false
    }
  },
  "tiles": [{
    "name": "Builds",
    "tileType": "HEADER",
    "configured": true,
    "bounds": {
      "top": 0,
      "left": 0,
      "width": 304,
      "height": 38
    },
    "tileFilter": {}
  }, {
    "name": "Custom chart",
    "tileType": "CUSTOM_CHARTING",
    "configured": true,
    "bounds": {
      "top": 342,
      "left": 0,
      "width": 304,
      "height": 304
    },
    "tileFilter": {},
    "filterConfig": {
      "type": "MIXED",
      "customName": "Builds",
      "defaultName": "Custom chart",
      "chartConfig": {
        "legendShown": true,
        "type": "TOP_LIST",
        "series": [{
          "metric": "ext:cloud.aws.codebuild.buildsSum",
          "aggregation": "NONE",
          "type": "LINE",
          "entityType": "IOT",
          "dimensions": [],
          "sortAscending": false,
          "sortColumn": true,
          "aggregationRate": "TOTAL"
        }],
        "resultMetadata": {}
      },
      "filtersPerEntityType": {}
    }
  }, {
    "name": "Custom chart",
    "tileType": "CUSTOM_CHARTING",
    "configured": true,
    "bounds": {
      "top": 38,
      "left": 0,
      "width": 304,
      "height": 304
    },
    "tileFilter": {},
    "filterConfig": {
      "type": "MIXED",
      "customName": "Builds",
      "defaultName": "Custom chart",
      "chartConfig": {
        "legendShown": true,
        "type": "TIMESERIES",
        "series": [{
          "metric": "ext:cloud.aws.codebuild.buildsSum",
          "aggregation": "NONE",
          "type": "LINE",
          "entityType": "IOT",
          "dimensions": [{
            "id": "0",
            "name": "dt.entity.custom_device",
            "values": [],
            "entityDimension": true
          }],
          "sortAscending": false,
          "sortColumn": true,
          "aggregationRate": "TOTAL"
        }],
        "resultMetadata": {}
      },
      "filtersPerEntityType": {}
    }
  }, {
    "name": "Custom chart",
    "tileType": "CUSTOM_CHARTING",
    "configured": true,
    "bounds": {
      "top": 38,
      "left": 304,
      "width": 304,
      "height": 304
    },
    "tileFilter": {},
    "filterConfig": {
      "type": "MIXED",
      "customName": "Failed builds",
      "defaultName": "Custom chart",
      "chartConfig": {
        "legendShown": true,
        "type": "TIMESERIES",
        "series": [{
          "metric": "ext:cloud.aws.codebuild.failedBuildsSum",
          "aggregation": "NONE",
          "type": "BAR",
          "entityType": "IOT",
          "dimensions": [{
            "id": "0",
            "name": "dt.entity.custom_device",
            "values": [],
            "entityDimension": true
          }],
          "sortAscending": false,
          "sortColumn": true,
          "aggregationRate": "TOTAL"
        }],
        "resultMetadata": {
          "CUSTOM_DEVICE-AD0A5B881B688DDE¦CUSTOM_DEVICE»CUSTOM_DEVICE-AD0A5B881B688DDE»trueext:cloud.aws.codebuild.failedBuildsSum|NONE|TOTAL|BAR|IOT": {
            "lastModified": 1594969124398,
            "customColor": "#ef651f"
          },
          "CUSTOM_DEVICE-4E348DF0DD31F7DE¦CUSTOM_DEVICE»CUSTOM_DEVICE-4E348DF0DD31F7DE»trueext:cloud.aws.codebuild.failedBuildsSum|NONE|TOTAL|BAR|IOT": {
            "lastModified": 1594969127246,
            "customColor": "#ffa86c"
          }
        }
      },
      "filtersPerEntityType": {}
    }
  }, {
    "name": "Custom chart",
    "tileType": "CUSTOM_CHARTING",
    "configured": true,
    "bounds": {
      "top": 342,
      "left": 304,
      "width": 304,
      "height": 304
    },
    "tileFilter": {},
    "filterConfig": {
      "type": "MIXED",
      "customName": "Failed builds",
      "defaultName": "Custom chart",
      "chartConfig": {
        "legendShown": true,
        "type": "TOP_LIST",
        "series": [{
          "metric": "ext:cloud.aws.codebuild.failedBuildsSum",
          "aggregation": "NONE",
          "type": "BAR",
          "entityType": "IOT",
          "dimensions": [{
            "id": "0",
            "name": "dt.entity.custom_device",
            "values": [],
            "entityDimension": true
          }],
          "sortAscending": false,
          "sortColumn": true,
          "aggregationRate": "TOTAL"
        }],
        "resultMetadata": {
          "CUSTOM_DEVICE-AD0A5B881B688DDE¦CUSTOM_DEVICE»CUSTOM_DEVICE-AD0A5B881B688DDE»trueext:cloud.aws.codebuild.failedBuildsSum|NONE|TOTAL|BAR|IOT": {
            "lastModified": 1594969124398,
            "customColor": "#ef651f"
          },
          "CUSTOM_DEVICE-4E348DF0DD31F7DE¦CUSTOM_DEVICE»CUSTOM_DEVICE-4E348DF0DD31F7DE»trueext:cloud.aws.codebuild.failedBuildsSum|NONE|TOTAL|BAR|IOT": {
            "lastModified": 1594969127246,
            "customColor": "#ffa86c"
          }
        }
      },
      "filtersPerEntityType": {}
    }
  }, {
    "name": "Custom chart",
    "tileType": "CUSTOM_CHARTING",
    "configured": true,
    "bounds": {
      "top": 646,
      "left": 646,
      "width": 304,
      "height": 304
    },
    "tileFilter": {},
    "filterConfig": {
      "type": "MIXED",
      "customName": "Duration",
      "defaultName": "Custom chart",
      "chartConfig": {
        "legendShown": true,
        "type": "TIMESERIES",
        "series": [{
          "metric": "ext:cloud.aws.codebuild.duration",
          "aggregation": "AVG",
          "type": "AREA",
          "entityType": "IOT",
          "dimensions": [],
          "sortAscending": false,
          "sortColumn": false,
          "aggregationRate": "TOTAL"
        }, {
          "metric": "ext:cloud.aws.codebuild.queuedDuration",
          "aggregation": "AVG",
          "type": "AREA",
          "entityType": "IOT",
          "dimensions": [],
          "sortAscending": false,
          "sortColumn": false,
          "aggregationRate": "TOTAL"
        }, {
          "metric": "ext:cloud.aws.codebuild.buildDuration",
          "aggregation": "AVG",
          "type": "AREA",
          "entityType": "IOT",
          "dimensions": [],
          "sortAscending": false,
          "sortColumn": true,
          "aggregationRate": "TOTAL"
        }],
        "resultMetadata": {
          "CUSTOM_DEVICE-AD0A5B881B688DDE¦CUSTOM_DEVICE»CUSTOM_DEVICE-AD0A5B881B688DDE»trueext:cloud.aws.codebuild.failedBuildsSum|NONE|TOTAL|BAR|IOT": {
            "lastModified": 1594969124398,
            "customColor": "#ef651f"
          },
          "nullext:cloud.aws.codebuild.queuedDuration|AVG|TOTAL|AREA|IOT": {
            "lastModified": 1594969302826,
            "customColor": "#2ab6f4"
          },
          "nullext:cloud.aws.codebuild.duration|AVG|TOTAL|AREA|IOT": {
            "lastModified": 1594969299896,
            "customColor": "#008cdb"
          },
          "CUSTOM_DEVICE-4E348DF0DD31F7DE¦CUSTOM_DEVICE»CUSTOM_DEVICE-4E348DF0DD31F7DE»trueext:cloud.aws.codebuild.failedBuildsSum|NONE|TOTAL|BAR|IOT": {
            "lastModified": 1594969127246,
            "customColor": "#ffa86c"
          }
        }
      },
      "filtersPerEntityType": {}
    }
  }, {
    "name": "Custom chart",
    "tileType": "CUSTOM_CHARTING",
    "configured": true,
    "bounds": {
      "top": 38,
      "left": 988,
      "width": 304,
      "height": 304
    },
    "tileFilter": {},
    "filterConfig": {
      "type": "MIXED",
      "customName": "CPU utilization",
      "defaultName": "Custom chart",
      "chartConfig": {
        "legendShown": true,
        "type": "TIMESERIES",
        "series": [{
          "metric": "ext:cloud.aws.codebuild.cpuUtilizedPercentByBuildIdBuildNumber",
          "aggregation": "SUM_DIMENSIONS",
          "type": "BAR",
          "entityType": "IOT",
          "dimensions": [{
            "id": "0",
            "name": "dt.entity.custom_device",
            "values": [],
            "entityDimension": true
          }],
          "sortAscending": false,
          "sortColumn": true,
          "aggregationRate": "TOTAL"
        }],
        "resultMetadata": {
          "CUSTOM_DEVICE-AD0A5B881B688DDE¦CUSTOM_DEVICE»CUSTOM_DEVICE-AD0A5B881B688DDE»trueext:cloud.aws.codebuild.failedBuildsSum|NONE|TOTAL|BAR|IOT": {
            "lastModified": 1594969124398,
            "customColor": "#ef651f"
          },
          "nullext:cloud.aws.codebuild.queuedDuration|AVG|TOTAL|AREA|IOT": {
            "lastModified": 1594969302826,
            "customColor": "#2ab6f4"
          },
          "nullext:cloud.aws.codebuild.duration|AVG|TOTAL|AREA|IOT": {
            "lastModified": 1594969299896,
            "customColor": "#008cdb"
          },
          "CUSTOM_DEVICE-4E348DF0DD31F7DE¦CUSTOM_DEVICE»CUSTOM_DEVICE-4E348DF0DD31F7DE»trueext:cloud.aws.codebuild.failedBuildsSum|NONE|TOTAL|BAR|IOT": {
            "lastModified": 1594969127246,
            "customColor": "#ffa86c"
          }
        }
      },
      "filtersPerEntityType": {}
    }
  }, {
    "name": "Duration",
    "tileType": "HEADER",
    "configured": true,
    "bounds": {
      "top": 0,
      "left": 646,
      "width": 304,
      "height": 38
    },
    "tileFilter": {}
  }, {
    "name": "Resource consumption",
    "tileType": "HEADER",
    "configured": true,
    "bounds": {
      "top": 0,
      "left": 988,
      "width": 304,
      "height": 38
    },
    "tileFilter": {}
  }, {
    "name": "Custom chart",
    "tileType": "CUSTOM_CHARTING",
    "configured": true,
    "bounds": {
      "top": 342,
      "left": 988,
      "width": 304,
      "height": 304
    },
    "tileFilter": {},
    "filterConfig": {
      "type": "MIXED",
      "customName": "Memory utilization",
      "defaultName": "Custom chart",
      "chartConfig": {
        "legendShown": true,
        "type": "TIMESERIES",
        "series": [{
          "metric": "ext:cloud.aws.codebuild.memoryUtilizedPercentByBuildIdBuildNumber",
          "aggregation": "SUM_DIMENSIONS",
          "type": "BAR",
          "entityType": "IOT",
          "dimensions": [{
            "id": "0",
            "name": "dt.entity.custom_device",
            "values": [],
            "entityDimension": true
          }],
          "sortAscending": false,
          "sortColumn": true,
          "aggregationRate": "TOTAL"
        }],
        "resultMetadata": {
          "CUSTOM_DEVICE-AD0A5B881B688DDE¦CUSTOM_DEVICE»CUSTOM_DEVICE-AD0A5B881B688DDE»trueext:cloud.aws.codebuild.failedBuildsSum|NONE|TOTAL|BAR|IOT": {
            "lastModified": 1594969124398,
            "customColor": "#ef651f"
          },
          "nullext:cloud.aws.codebuild.queuedDuration|AVG|TOTAL|AREA|IOT": {
            "lastModified": 1594969302826,
            "customColor": "#2ab6f4"
          },
          "nullext:cloud.aws.codebuild.duration|AVG|TOTAL|AREA|IOT": {
            "lastModified": 1594969299896,
            "customColor": "#008cdb"
          },
          "CUSTOM_DEVICE-4E348DF0DD31F7DE¦CUSTOM_DEVICE»CUSTOM_DEVICE-4E348DF0DD31F7DE»trueext:cloud.aws.codebuild.failedBuildsSum|NONE|TOTAL|BAR|IOT": {
            "lastModified": 1594969127246,
            "customColor": "#ffa86c"
          }
        }
      },
      "filtersPerEntityType": {}
    }
  }, {
    "name": "Custom chart",
    "tileType": "CUSTOM_CHARTING",
    "configured": true,
    "bounds": {
      "top": 646,
      "left": 988,
      "width": 304,
      "height": 304
    },
    "tileFilter": {},
    "filterConfig": {
      "type": "MIXED",
      "customName": "Storage utilization",
      "defaultName": "Custom chart",
      "chartConfig": {
        "legendShown": true,
        "type": "TIMESERIES",
        "series": [{
          "metric": "ext:cloud.aws.codebuild.storageReadBytesByBuildIdBuildNumber",
          "aggregation": "AVG",
          "type": "BAR",
          "entityType": "IOT",
          "dimensions": [{
            "id": "0",
            "name": "dt.entity.custom_device",
            "values": [],
            "entityDimension": true
          }],
          "sortAscending": false,
          "sortColumn": false,
          "aggregationRate": "TOTAL"
        }, {
          "metric": "ext:cloud.aws.codebuild.storageWriteBytesByBuildIdBuildNumber",
          "aggregation": "AVG",
          "type": "BAR",
          "entityType": "IOT",
          "dimensions": [{
            "id": "0",
            "name": "dt.entity.custom_device",
            "values": [],
            "entityDimension": true
          }],
          "sortAscending": false,
          "sortColumn": true,
          "aggregationRate": "TOTAL"
        }],
        "resultMetadata": {
          "CUSTOM_DEVICE-AD0A5B881B688DDE¦CUSTOM_DEVICE»CUSTOM_DEVICE-AD0A5B881B688DDE»trueext:cloud.aws.codebuild.failedBuildsSum|NONE|TOTAL|BAR|IOT": {
            "lastModified": 1594969124398,
            "customColor": "#ef651f"
          },
          "nullext:cloud.aws.codebuild.queuedDuration|AVG|TOTAL|AREA|IOT": {
            "lastModified": 1594969302826,
            "customColor": "#2ab6f4"
          },
          "nullext:cloud.aws.codebuild.duration|AVG|TOTAL|AREA|IOT": {
            "lastModified": 1594969299896,
            "customColor": "#008cdb"
          },
          "CUSTOM_DEVICE-4E348DF0DD31F7DE¦CUSTOM_DEVICE»CUSTOM_DEVICE-4E348DF0DD31F7DE»trueext:cloud.aws.codebuild.failedBuildsSum|NONE|TOTAL|BAR|IOT": {
            "lastModified": 1594969127246,
            "customColor": "#ffa86c"
          }
        }
      },
      "filtersPerEntityType": {}
    }
  }, {
    "name": "Custom chart",
    "tileType": "CUSTOM_CHARTING",
    "configured": true,
    "bounds": {
      "top": 38,
      "left": 646,
      "width": 304,
      "height": 304
    },
    "tileFilter": {},
    "filterConfig": {
      "type": "MIXED",
      "customName": "Build duration",
      "defaultName": "Custom chart",
      "chartConfig": {
        "legendShown": true,
        "type": "TIMESERIES",
        "series": [{
          "metric": "ext:cloud.aws.codebuild.buildDuration",
          "aggregation": "AVG",
          "type": "LINE",
          "entityType": "IOT",
          "dimensions": [{
            "id": "0",
            "name": "dt.entity.custom_device",
            "values": [],
            "entityDimension": true
          }],
          "sortAscending": false,
          "sortColumn": true,
          "aggregationRate": "TOTAL"
        }],
        "resultMetadata": {
          "CUSTOM_DEVICE-AD0A5B881B688DDE¦CUSTOM_DEVICE»CUSTOM_DEVICE-AD0A5B881B688DDE»trueext:cloud.aws.codebuild.failedBuildsSum|NONE|TOTAL|BAR|IOT": {
            "lastModified": 1594969124398,
            "customColor": "#ef651f"
          },
          "nullext:cloud.aws.codebuild.queuedDuration|AVG|TOTAL|AREA|IOT": {
            "lastModified": 1594969302826,
            "customColor": "#2ab6f4"
          },
          "nullext:cloud.aws.codebuild.duration|AVG|TOTAL|AREA|IOT": {
            "lastModified": 1594969299896,
            "customColor": "#008cdb"
          },
          "CUSTOM_DEVICE-4E348DF0DD31F7DE¦CUSTOM_DEVICE»CUSTOM_DEVICE-4E348DF0DD31F7DE»trueext:cloud.aws.codebuild.failedBuildsSum|NONE|TOTAL|BAR|IOT": {
            "lastModified": 1594969127246,
            "customColor": "#ffa86c"
          }
        }
      },
      "filtersPerEntityType": {}
    }
  }, {
    "name": "Custom chart",
    "tileType": "CUSTOM_CHARTING",
    "configured": true,
    "bounds": {
      "top": 342,
      "left": 646,
      "width": 304,
      "height": 304
    },
    "tileFilter": {},
    "filterConfig": {
      "type": "MIXED",
      "customName": "Queued duration",
      "defaultName": "Custom chart",
      "chartConfig": {
        "legendShown": true,
        "type": "TOP_LIST",
        "series": [{
          "metric": "ext:cloud.aws.codebuild.queuedDuration",
          "aggregation": "AVG",
          "type": "LINE",
          "entityType": "IOT",
          "dimensions": [{
            "id": "0",
            "name": "dt.entity.custom_device",
            "values": [],
            "entityDimension": true
          }],
          "sortAscending": false,
          "sortColumn": true,
          "aggregationRate": "TOTAL"
        }],
        "resultMetadata": {
          "CUSTOM_DEVICE-AD0A5B881B688DDE¦CUSTOM_DEVICE»CUSTOM_DEVICE-AD0A5B881B688DDE»trueext:cloud.aws.codebuild.failedBuildsSum|NONE|TOTAL|BAR|IOT": {
            "lastModified": 1594969124398,
            "customColor": "#ef651f"
          },
          "nullext:cloud.aws.codebuild.queuedDuration|AVG|TOTAL|AREA|IOT": {
            "lastModified": 1594969302826,
            "customColor": "#2ab6f4"
          },
          "nullext:cloud.aws.codebuild.duration|AVG|TOTAL|AREA|IOT": {
            "lastModified": 1594969299896,
            "customColor": "#008cdb"
          },
          "CUSTOM_DEVICE-4E348DF0DD31F7DE¦CUSTOM_DEVICE»CUSTOM_DEVICE-4E348DF0DD31F7DE»trueext:cloud.aws.codebuild.failedBuildsSum|NONE|TOTAL|BAR|IOT": {
            "lastModified": 1594969127246,
            "customColor": "#ffa86c"
          }
        }
      },
      "filtersPerEntityType": {}
    }
  }]
}