{
  "metadata": {},
  "dashboardMetadata": {
    "name": "Amazon Keyspaces",
    "shared": false,
    "sharingDetails": {
      "linkShared": true,
      "published": false
    },
    "dashboardFilter": {
      "timeframe": "Today",
      "managementZone": null
    }
  },
  "tiles": [
    {
      "name": "Usage",
      "tileType": "HEADER",
      "configured": true,
      "bounds": {
        "top": 0,
        "left": 0,
        "width": 304,
        "height": 38
      },
      "tileFilter": {
        "timeframe": null,
        "managementZone": null
      }
    },
    {
      "name": "Custom chart",
      "tileType": "CUSTOM_CHARTING",
      "configured": true,
      "bounds": {
        "top": 38,
        "left": 608,
        "width": 304,
        "height": 304
      },
      "tileFilter": {
        "timeframe": null,
        "managementZone": null
      },
      "filterConfig": {
        "type": "MIXED",
        "customName": "Successful Request Count Sum (by Keyspace and TableName)",
        "defaultName": "Custom chart",
        "chartConfig": {
          "legendShown": true,
          "type": "TOP_LIST",
          "series": [
            {
              "metric": "ext:cloud.aws.cassandra.successfulRequestCountSumByOperationTableName",
              "aggregation": "NONE",
              "percentile": null,
              "type": "LINE",
              "entityType": "IOT",
              "dimensions": [
                {
                  "id": "0",
                  "name": "dt.entity.custom_device",
                  "values": [],
                  "entityDimension": true
                },
                {
                  "id": "2",
                  "name": "TableName",
                  "values": [],
                  "entityDimension": false
                }
              ],
              "sortAscending": false,
              "sortColumn": true,
              "aggregationRate": "TOTAL"
            }
          ],
          "resultMetadata": {}
        },
        "filtersPerEntityType": {}
      }
    },
    {
      "name": "Custom chart",
      "tileType": "CUSTOM_CHARTING",
      "configured": true,
      "bounds": {
        "top": 342,
        "left": 608,
        "width": 304,
        "height": 304
      },
      "tileFilter": {
        "timeframe": null,
        "managementZone": null
      },
      "filterConfig": {
        "type": "MIXED",
        "customName": "SuccessfulRequestLatency Avg (by Keyspace, Operation, and TableName)",
        "defaultName": "Custom chart",
        "chartConfig": {
          "legendShown": true,
          "type": "TIMESERIES",
          "series": [
            {
              "metric": "ext:cloud.aws.cassandra.successfulRequestLatencyByOperationTableName",
              "aggregation": "AVG",
              "percentile": null,
              "type": "LINE",
              "entityType": "IOT",
              "dimensions": [
                {
                  "id": "0",
                  "name": "dt.entity.custom_device",
                  "values": [],
                  "entityDimension": true
                },
                {
                  "id": "1",
                  "name": "Operation",
                  "values": [],
                  "entityDimension": false
                },
                {
                  "id": "2",
                  "name": "TableName",
                  "values": [],
                  "entityDimension": false
                }
              ],
              "sortAscending": false,
              "sortColumn": true,
              "aggregationRate": "TOTAL"
            }
          ],
          "resultMetadata": {}
        },
        "filtersPerEntityType": {}
      }
    },
    {
      "name": "Failures",
      "tileType": "HEADER",
      "configured": true,
      "bounds": {
        "top": 0,
        "left": 1216,
        "width": 304,
        "height": 38
      },
      "tileFilter": {
        "timeframe": null,
        "managementZone": null
      }
    },
    {
      "name": "Custom chart",
      "tileType": "CUSTOM_CHARTING",
      "configured": true,
      "bounds": {
        "top": 38,
        "left": 1216,
        "width": 304,
        "height": 304
      },
      "tileFilter": {
        "timeframe": null,
        "managementZone": null
      },
      "filterConfig": {
        "type": "MIXED",
        "customName": "UserErrors Sum (by Keyspace, Operation and TableName)",
        "defaultName": "Custom chart",
        "chartConfig": {
          "legendShown": true,
          "type": "TOP_LIST",
          "series": [
            {
              "metric": "ext:cloud.aws.cassandra.userErrorsSumByOperationTableName",
              "aggregation": "NONE",
              "percentile": null,
              "type": "LINE",
              "entityType": "IOT",
              "dimensions": [
                {
                  "id": "0",
                  "name": "dt.entity.custom_device",
                  "values": [],
                  "entityDimension": true
                },
                {
                  "id": "1",
                  "name": "Operation",
                  "values": [],
                  "entityDimension": false
                },
                {
                  "id": "2",
                  "name": "TableName",
                  "values": [],
                  "entityDimension": false
                }
              ],
              "sortAscending": false,
              "sortColumn": true,
              "aggregationRate": "TOTAL"
            }
          ],
          "resultMetadata": {}
        },
        "filtersPerEntityType": {}
      }
    },
    {
      "name": "Custom chart",
      "tileType": "CUSTOM_CHARTING",
      "configured": true,
      "bounds": {
        "top": 38,
        "left": 1520,
        "width": 304,
        "height": 304
      },
      "tileFilter": {
        "timeframe": null,
        "managementZone": null
      },
      "filterConfig": {
        "type": "MIXED",
        "customName": "ConditionalCheckFailed Sum (by Keyspace, Operation and TableName)",
        "defaultName": "Custom chart",
        "chartConfig": {
          "legendShown": true,
          "type": "TOP_LIST",
          "series": [
            {
              "metric": "ext:cloud.aws.cassandra.conditionalCheckFailedSumByOperationTableName",
              "aggregation": "NONE",
              "percentile": null,
              "type": "LINE",
              "entityType": "IOT",
              "dimensions": [
                {
                  "id": "0",
                  "name": "dt.entity.custom_device",
                  "values": [],
                  "entityDimension": true
                },
                {
                  "id": "1",
                  "name": "Operation",
                  "values": [],
                  "entityDimension": false
                },
                {
                  "id": "2",
                  "name": "TableName",
                  "values": [],
                  "entityDimension": false
                }
              ],
              "sortAscending": false,
              "sortColumn": true,
              "aggregationRate": "TOTAL"
            }
          ],
          "resultMetadata": {}
        },
        "filtersPerEntityType": {}
      }
    },
    {
      "name": "Custom chart",
      "tileType": "CUSTOM_CHARTING",
      "configured": true,
      "bounds": {
        "top": 342,
        "left": 1216,
        "width": 304,
        "height": 304
      },
      "tileFilter": {
        "timeframe": null,
        "managementZone": null
      },
      "filterConfig": {
        "type": "MIXED",
        "customName": "SystemErrors Sum (by Keyspace,Operation and TableName)",
        "defaultName": "Custom chart",
        "chartConfig": {
          "legendShown": true,
          "type": "TOP_LIST",
          "series": [
            {
              "metric": "ext:cloud.aws.cassandra.systemErrorsSumByOperationTableName",
              "aggregation": "NONE",
              "percentile": null,
              "type": "LINE",
              "entityType": "IOT",
              "dimensions": [
                {
                  "id": "0",
                  "name": "dt.entity.custom_device",
                  "values": [],
                  "entityDimension": true
                },
                {
                  "id": "1",
                  "name": "Operation",
                  "values": [],
                  "entityDimension": false
                },
                {
                  "id": "2",
                  "name": "TableName",
                  "values": [],
                  "entityDimension": false
                }
              ],
              "sortAscending": false,
              "sortColumn": true,
              "aggregationRate": "TOTAL"
            }
          ],
          "resultMetadata": {}
        },
        "filtersPerEntityType": {}
      }
    },
    {
      "name": "Custom chart",
      "tileType": "CUSTOM_CHARTING",
      "configured": true,
      "bounds": {
        "top": 38,
        "left": 304,
        "width": 304,
        "height": 304
      },
      "tileFilter": {
        "timeframe": null,
        "managementZone": null
      },
      "filterConfig": {
        "type": "MIXED",
        "customName": "Read Capacity Units (by Keyspace)",
        "defaultName": "Custom chart",
        "chartConfig": {
          "legendShown": true,
          "type": "TIMESERIES",
          "series": [
            {
              "metric": "ext:cloud.aws.cassandra.consumedReadCapacityUnitsSumByTableName",
              "aggregation": "NONE",
              "percentile": null,
              "type": "BAR",
              "entityType": "IOT",
              "dimensions": [
                {
                  "id": "0",
                  "name": "dt.entity.custom_device",
                  "values": [],
                  "entityDimension": true
                }
              ],
              "sortAscending": false,
              "sortColumn": false,
              "aggregationRate": "TOTAL"
            },
            {
              "metric": "ext:cloud.aws.cassandra.provisionedReadCapacityUnitsByTableName",
              "aggregation": "MAX",
              "percentile": null,
              "type": "LINE",
              "entityType": "IOT",
              "dimensions": [
                {
                  "id": "0",
                  "name": "dt.entity.custom_device",
                  "values": [],
                  "entityDimension": true
                }
              ],
              "sortAscending": false,
              "sortColumn": true,
              "aggregationRate": "TOTAL"
            }
          ],
          "resultMetadata": {}
        },
        "filtersPerEntityType": {}
      }
    },
    {
      "name": "Custom chart",
      "tileType": "CUSTOM_CHARTING",
      "configured": true,
      "bounds": {
        "top": 38,
        "left": 0,
        "width": 304,
        "height": 304
      },
      "tileFilter": {
        "timeframe": null,
        "managementZone": null
      },
      "filterConfig": {
        "type": "MIXED",
        "customName": "Write Capacity Units (by Keyspace)",
        "defaultName": "Custom chart",
        "chartConfig": {
          "legendShown": true,
          "type": "TIMESERIES",
          "series": [
            {
              "metric": "ext:cloud.aws.cassandra.consumedWriteCapacityUnitsSumByTableName",
              "aggregation": "NONE",
              "percentile": null,
              "type": "BAR",
              "entityType": "IOT",
              "dimensions": [
                {
                  "id": "0",
                  "name": "dt.entity.custom_device",
                  "values": [],
                  "entityDimension": true
                }
              ],
              "sortAscending": false,
              "sortColumn": false,
              "aggregationRate": "TOTAL"
            },
            {
              "metric": "ext:cloud.aws.cassandra.provisionedWriteCapacityUnitsByTableName",
              "aggregation": "MAX",
              "percentile": null,
              "type": "LINE",
              "entityType": "IOT",
              "dimensions": [
                {
                  "id": "0",
                  "name": "dt.entity.custom_device",
                  "values": [],
                  "entityDimension": true
                }
              ],
              "sortAscending": false,
              "sortColumn": true,
              "aggregationRate": "TOTAL"
            }
          ],
          "resultMetadata": {}
        },
        "filtersPerEntityType": {}
      }
    },
    {
      "name": "Custom chart",
      "tileType": "CUSTOM_CHARTING",
      "configured": true,
      "bounds": {
        "top": 342,
        "left": 912,
        "width": 304,
        "height": 304
      },
      "tileFilter": {
        "timeframe": null,
        "managementZone": null
      },
      "filterConfig": {
        "type": "MIXED",
        "customName": "Returned Item Count By Select (by Keyspace and TableName)",
        "defaultName": "Custom chart",
        "chartConfig": {
          "legendShown": true,
          "type": "PIE",
          "series": [
            {
              "metric": "ext:cloud.aws.cassandra.returnedItemCountBySelectSumByOperationTableName",
              "aggregation": "NONE",
              "percentile": null,
              "type": "BAR",
              "entityType": "IOT",
              "dimensions": [
                {
                  "id": "0",
                  "name": "dt.entity.custom_device",
                  "values": [],
                  "entityDimension": true
                },
                {
                  "id": "2",
                  "name": "TableName",
                  "values": [],
                  "entityDimension": false
                }
              ],
              "sortAscending": false,
              "sortColumn": true,
              "aggregationRate": "TOTAL"
            }
          ],
          "resultMetadata": {}
        },
        "filtersPerEntityType": {}
      }
    },
    {
      "name": "Custom chart",
      "tileType": "CUSTOM_CHARTING",
      "configured": true,
      "bounds": {
        "top": 646,
        "left": 304,
        "width": 304,
        "height": 304
      },
      "tileFilter": {
        "timeframe": null,
        "managementZone": null
      },
      "filterConfig": {
        "type": "MIXED",
        "customName": "Account Max Reads (by Region)",
        "defaultName": "Custom chart",
        "chartConfig": {
          "legendShown": true,
          "type": "TIMESERIES",
          "series": [
            {
              "metric": "ext:cloud.aws.cassandra.accountMaxReadsByRegion",
              "aggregation": "MAX",
              "percentile": null,
              "type": "LINE",
              "entityType": "MONITORED_ENTITY˟CUSTOM_DEVICE_GROUP",
              "dimensions": [
                {
                  "id": "1",
                  "name": "Region",
                  "values": [],
                  "entityDimension": false
                }
              ],
              "sortAscending": false,
              "sortColumn": false,
              "aggregationRate": "TOTAL"
            },
            {
              "metric": "ext:cloud.aws.cassandra.accountMaxTableLevelReadsByRegion",
              "aggregation": "MAX",
              "percentile": null,
              "type": "LINE",
              "entityType": "MONITORED_ENTITY˟CUSTOM_DEVICE_GROUP",
              "dimensions": [
                {
                  "id": "1",
                  "name": "Region",
                  "values": [],
                  "entityDimension": false
                }
              ],
              "sortAscending": false,
              "sortColumn": true,
              "aggregationRate": "TOTAL"
            }
          ],
          "resultMetadata": {
            "null¦Region»us-east-1»falseext:cloud.aws.cassandra.accountMaxTableLevelReadsByRegion|MAX|TOTAL|LINE|MONITORED_ENTITY˟CUSTOM_DEVICE_GROUP": {
              "lastModified": 1593119527002,
              "customColor": "#00a1b2"
            }
          }
        },
        "filtersPerEntityType": {}
      }
    },
    {
      "name": "Custom chart",
      "tileType": "CUSTOM_CHARTING",
      "configured": true,
      "bounds": {
        "top": 646,
        "left": 0,
        "width": 304,
        "height": 304
      },
      "tileFilter": {
        "timeframe": null,
        "managementZone": null
      },
      "filterConfig": {
        "type": "MIXED",
        "customName": "Account Max Writes (by Region)",
        "defaultName": "Custom chart",
        "chartConfig": {
          "legendShown": true,
          "type": "TIMESERIES",
          "series": [
            {
              "metric": "ext:cloud.aws.cassandra.accountMaxWritesByRegion",
              "aggregation": "MAX",
              "percentile": null,
              "type": "LINE",
              "entityType": "MONITORED_ENTITY˟CUSTOM_DEVICE_GROUP",
              "dimensions": [
                {
                  "id": "1",
                  "name": "Region",
                  "values": [],
                  "entityDimension": false
                }
              ],
              "sortAscending": false,
              "sortColumn": false,
              "aggregationRate": "TOTAL"
            },
            {
              "metric": "ext:cloud.aws.cassandra.accountMaxTableLevelWritesByRegion",
              "aggregation": "MAX",
              "percentile": null,
              "type": "LINE",
              "entityType": "MONITORED_ENTITY˟CUSTOM_DEVICE_GROUP",
              "dimensions": [
                {
                  "id": "1",
                  "name": "Region",
                  "values": [],
                  "entityDimension": false
                }
              ],
              "sortAscending": false,
              "sortColumn": true,
              "aggregationRate": "TOTAL"
            }
          ],
          "resultMetadata": {
            "null¦Region»us-east-1»falseext:cloud.aws.cassandra.accountMaxTableLevelWritesByRegion|MAX|TOTAL|LINE|MONITORED_ENTITY˟CUSTOM_DEVICE_GROUP": {
              "lastModified": 1593119617251,
              "customColor": "#00a1b2"
            }
          }
        },
        "filtersPerEntityType": {}
      }
    },
    {
      "name": "Performance",
      "tileType": "HEADER",
      "configured": true,
      "bounds": {
        "top": 0,
        "left": 608,
        "width": 304,
        "height": 38
      },
      "tileFilter": {
        "timeframe": null,
        "managementZone": null
      }
    },
    {
      "name": "Custom chart",
      "tileType": "CUSTOM_CHARTING",
      "configured": true,
      "bounds": {
        "top": 342,
        "left": 0,
        "width": 304,
        "height": 304
      },
      "tileFilter": {
        "timeframe": null,
        "managementZone": null
      },
      "filterConfig": {
        "type": "MIXED",
        "customName": "Read Capacity Utilization (by Region)",
        "defaultName": "Custom chart",
        "chartConfig": {
          "legendShown": true,
          "type": "TIMESERIES",
          "series": [
            {
              "metric": "ext:cloud.aws.cassandra.accountProvisionedReadCapacityUtilizationByRegion",
              "aggregation": "MAX",
              "percentile": null,
              "type": "LINE",
              "entityType": "MONITORED_ENTITY˟CUSTOM_DEVICE_GROUP",
              "dimensions": [
                {
                  "id": "1",
                  "name": "Region",
                  "values": [],
                  "entityDimension": false
                }
              ],
              "sortAscending": false,
              "sortColumn": false,
              "aggregationRate": "TOTAL"
            },
            {
              "metric": "ext:cloud.aws.cassandra.maxProvisionedTableReadCapacityUtilizationByRegion",
              "aggregation": "MAX",
              "percentile": null,
              "type": "LINE",
              "entityType": "MONITORED_ENTITY˟CUSTOM_DEVICE_GROUP",
              "dimensions": [
                {
                  "id": "1",
                  "name": "Region",
                  "values": [],
                  "entityDimension": false
                }
              ],
              "sortAscending": false,
              "sortColumn": true,
              "aggregationRate": "TOTAL"
            }
          ],
          "resultMetadata": {}
        },
        "filtersPerEntityType": {}
      }
    },
    {
      "name": "Custom chart",
      "tileType": "CUSTOM_CHARTING",
      "configured": true,
      "bounds": {
        "top": 342,
        "left": 304,
        "width": 304,
        "height": 304
      },
      "tileFilter": {
        "timeframe": null,
        "managementZone": null
      },
      "filterConfig": {
        "type": "MIXED",
        "customName": "Write Capacity Utilization (by Region)",
        "defaultName": "Custom chart",
        "chartConfig": {
          "legendShown": true,
          "type": "TIMESERIES",
          "series": [
            {
              "metric": "ext:cloud.aws.cassandra.accountProvisionedWriteCapacityUtilizationByRegion",
              "aggregation": "MAX",
              "percentile": null,
              "type": "LINE",
              "entityType": "MONITORED_ENTITY˟CUSTOM_DEVICE_GROUP",
              "dimensions": [
                {
                  "id": "1",
                  "name": "Region",
                  "values": [],
                  "entityDimension": false
                }
              ],
              "sortAscending": false,
              "sortColumn": false,
              "aggregationRate": "TOTAL"
            },
            {
              "metric": "ext:cloud.aws.cassandra.maxProvisionedTableWriteCapacityUtilizationByRegion",
              "aggregation": "MAX",
              "percentile": null,
              "type": "LINE",
              "entityType": "MONITORED_ENTITY˟CUSTOM_DEVICE_GROUP",
              "dimensions": [
                {
                  "id": "1",
                  "name": "Region",
                  "values": [],
                  "entityDimension": false
                }
              ],
              "sortAscending": false,
              "sortColumn": true,
              "aggregationRate": "TOTAL"
            }
          ],
          "resultMetadata": {}
        },
        "filtersPerEntityType": {}
      }
    },
    {
      "name": "Custom chart",
      "tileType": "CUSTOM_CHARTING",
      "configured": true,
      "bounds": {
        "top": 38,
        "left": 912,
        "width": 304,
        "height": 304
      },
      "tileFilter": {
        "timeframe": null,
        "managementZone": null
      },
      "filterConfig": {
        "type": "MIXED",
        "customName": "Successful Request Count Sum (by Operation)",
        "defaultName": "Custom chart",
        "chartConfig": {
          "legendShown": true,
          "type": "TOP_LIST",
          "series": [
            {
              "metric": "ext:cloud.aws.cassandra.successfulRequestCountSumByOperationTableName",
              "aggregation": "NONE",
              "percentile": null,
              "type": "LINE",
              "entityType": "IOT",
              "dimensions": [
                {
                  "id": "1",
                  "name": "Operation",
                  "values": [],
                  "entityDimension": false
                }
              ],
              "sortAscending": false,
              "sortColumn": true,
              "aggregationRate": "TOTAL"
            }
          ],
          "resultMetadata": {}
        },
        "filtersPerEntityType": {}
      }
    }
  ]
}
