{
  "metadata": {
    "configurationVersions": [
      3
    ],
    "clusterVersion": "1.198.1.20200703-040410"
  },
  "dashboardMetadata": {
    "name": "Azure Data Factory v2",
    "shared": false,
    "sharingDetails": {
      "linkShared": true,
      "published": false
    },
    "dashboardFilter": {
      "timeframe": "",
      "managementZone": null
    }
  },
  "tiles": [
    {
      "name": "Custom chart",
      "tileType": "CUSTOM_CHARTING",
      "configured": true,
      "bounds": {
        "top": 38,
        "left": 0,
        "width": 304,
        "height": 304
      },
      "tileFilter": {
        "timeframe": null,
        "managementZone": null
      },
      "filterConfig": {
        "type": "MIXED",
        "customName": "Succeeded pipeline runs metrics",
        "defaultName": "Custom chart",
        "chartConfig": {
          "legendShown": true,
          "type": "TOP_LIST",
          "series": [
            {
              "metric": "ext:cloud.azure.microsoft_datafactory.factories.pipelinesucceededruns",
              "aggregation": "SUM",
              "percentile": null,
              "type": "LINE",
              "entityType": "IOT",
              "dimensions": [
                {
                  "id": "0",
                  "name": "dt.entity.custom_device",
                  "values": [],
                  "entityDimension": true
                }
              ],
              "sortAscending": false,
              "sortColumn": true,
              "aggregationRate": "TOTAL"
            }
          ],
          "resultMetadata": {}
        },
        "filtersPerEntityType": {}
      }
    },
    {
      "name": "Usage",
      "tileType": "HEADER",
      "configured": true,
      "bounds": {
        "top": 0,
        "left": 0,
        "width": 304,
        "height": 38
      },
      "tileFilter": {
        "timeframe": null,
        "managementZone": null
      }
    },
    {
      "name": "Custom chart",
      "tileType": "CUSTOM_CHARTING",
      "configured": true,
      "bounds": {
        "top": 38,
        "left": 304,
        "width": 304,
        "height": 304
      },
      "tileFilter": {
        "timeframe": null,
        "managementZone": null
      },
      "filterConfig": {
        "type": "MIXED",
        "customName": "Pipeline runs metrics",
        "defaultName": "Custom chart",
        "chartConfig": {
          "legendShown": true,
          "type": "TIMESERIES",
          "series": [
            {
              "metric": "ext:cloud.azure.microsoft_datafactory.factories.pipelinesucceededruns",
              "aggregation": "SUM",
              "percentile": null,
              "type": "BAR",
              "entityType": "IOT",
              "dimensions": [
                {
                  "id": "0",
                  "name": "dt.entity.custom_device",
                  "values": [],
                  "entityDimension": true
                }
              ],
              "sortAscending": false,
              "sortColumn": false,
              "aggregationRate": "TOTAL"
            },
            {
              "metric": "ext:cloud.azure.microsoft_datafactory.factories.pipelinefailedruns",
              "aggregation": "SUM",
              "percentile": null,
              "type": "BAR",
              "entityType": "IOT",
              "dimensions": [
                {
                  "id": "0",
                  "name": "dt.entity.custom_device",
                  "values": [],
                  "entityDimension": true
                }
              ],
              "sortAscending": false,
              "sortColumn": true,
              "aggregationRate": "TOTAL"
            }
          ],
          "resultMetadata": {}
        },
        "filtersPerEntityType": {}
      }
    },
    {
      "name": "Custom chart",
      "tileType": "CUSTOM_CHARTING",
      "configured": true,
      "bounds": {
        "top": 342,
        "left": 0,
        "width": 304,
        "height": 304
      },
      "tileFilter": {
        "timeframe": null,
        "managementZone": null
      },
      "filterConfig": {
        "type": "MIXED",
        "customName": "Succeeded activity runs metrics",
        "defaultName": "Custom chart",
        "chartConfig": {
          "legendShown": true,
          "type": "TOP_LIST",
          "series": [
            {
              "metric": "ext:cloud.azure.microsoft_datafactory.factories.activitysucceededruns",
              "aggregation": "SUM",
              "percentile": null,
              "type": "LINE",
              "entityType": "IOT",
              "dimensions": [
                {
                  "id": "0",
                  "name": "dt.entity.custom_device",
                  "values": [],
                  "entityDimension": true
                }
              ],
              "sortAscending": false,
              "sortColumn": true,
              "aggregationRate": "TOTAL"
            }
          ],
          "resultMetadata": {}
        },
        "filtersPerEntityType": {}
      }
    },
    {
      "name": "Custom chart",
      "tileType": "CUSTOM_CHARTING",
      "configured": true,
      "bounds": {
        "top": 342,
        "left": 304,
        "width": 304,
        "height": 304
      },
      "tileFilter": {
        "timeframe": null,
        "managementZone": null
      },
      "filterConfig": {
        "type": "MIXED",
        "customName": "Activity runs metrics",
        "defaultName": "Custom chart",
        "chartConfig": {
          "legendShown": true,
          "type": "TIMESERIES",
          "series": [
            {
              "metric": "ext:cloud.azure.microsoft_datafactory.factories.activitysucceededruns",
              "aggregation": "SUM",
              "percentile": null,
              "type": "BAR",
              "entityType": "IOT",
              "dimensions": [
                {
                  "id": "0",
                  "name": "dt.entity.custom_device",
                  "values": [],
                  "entityDimension": true
                }
              ],
              "sortAscending": false,
              "sortColumn": false,
              "aggregationRate": "TOTAL"
            },
            {
              "metric": "ext:cloud.azure.microsoft_datafactory.factories.activityfailedruns",
              "aggregation": "SUM",
              "percentile": null,
              "type": "BAR",
              "entityType": "IOT",
              "dimensions": [
                {
                  "id": "0",
                  "name": "dt.entity.custom_device",
                  "values": [],
                  "entityDimension": true
                }
              ],
              "sortAscending": false,
              "sortColumn": true,
              "aggregationRate": "TOTAL"
            }
          ],
          "resultMetadata": {}
        },
        "filtersPerEntityType": {}
      }
    },
    {
      "name": "Custom chart",
      "tileType": "CUSTOM_CHARTING",
      "configured": true,
      "bounds": {
        "top": 646,
        "left": 0,
        "width": 304,
        "height": 304
      },
      "tileFilter": {
        "timeframe": null,
        "managementZone": null
      },
      "filterConfig": {
        "type": "MIXED",
        "customName": "Succeeded trigger runs metrics",
        "defaultName": "Custom chart",
        "chartConfig": {
          "legendShown": true,
          "type": "TOP_LIST",
          "series": [
            {
              "metric": "ext:cloud.azure.microsoft_datafactory.factories.triggersucceededruns",
              "aggregation": "SUM",
              "percentile": null,
              "type": "LINE",
              "entityType": "IOT",
              "dimensions": [
                {
                  "id": "0",
                  "name": "dt.entity.custom_device",
                  "values": [],
                  "entityDimension": true
                }
              ],
              "sortAscending": false,
              "sortColumn": true,
              "aggregationRate": "TOTAL"
            }
          ],
          "resultMetadata": {}
        },
        "filtersPerEntityType": {}
      }
    },
    {
      "name": "Custom chart",
      "tileType": "CUSTOM_CHARTING",
      "configured": true,
      "bounds": {
        "top": 646,
        "left": 304,
        "width": 304,
        "height": 304
      },
      "tileFilter": {
        "timeframe": null,
        "managementZone": null
      },
      "filterConfig": {
        "type": "MIXED",
        "customName": "Trigger runs metrics",
        "defaultName": "Custom chart",
        "chartConfig": {
          "legendShown": true,
          "type": "TIMESERIES",
          "series": [
            {
              "metric": "ext:cloud.azure.microsoft_datafactory.factories.triggersucceededruns",
              "aggregation": "SUM",
              "percentile": null,
              "type": "BAR",
              "entityType": "IOT",
              "dimensions": [
                {
                  "id": "0",
                  "name": "dt.entity.custom_device",
                  "values": [],
                  "entityDimension": true
                }
              ],
              "sortAscending": false,
              "sortColumn": false,
              "aggregationRate": "TOTAL"
            },
            {
              "metric": "ext:cloud.azure.microsoft_datafactory.factories.triggerfailedruns",
              "aggregation": "SUM",
              "percentile": null,
              "type": "BAR",
              "entityType": "IOT",
              "dimensions": [
                {
                  "id": "0",
                  "name": "dt.entity.custom_device",
                  "values": [],
                  "entityDimension": true
                }
              ],
              "sortAscending": false,
              "sortColumn": true,
              "aggregationRate": "TOTAL"
            }
          ],
          "resultMetadata": {}
        },
        "filtersPerEntityType": {}
      }
    },
    {
      "name": "Custom chart",
      "tileType": "CUSTOM_CHARTING",
      "configured": true,
      "bounds": {
        "top": 38,
        "left": 646,
        "width": 304,
        "height": 304
      },
      "tileFilter": {
        "timeframe": null,
        "managementZone": null
      },
      "filterConfig": {
        "type": "MIXED",
        "customName": "Integration runtime CPU utilization",
        "defaultName": "Custom chart",
        "chartConfig": {
          "legendShown": true,
          "type": "TIMESERIES",
          "series": [
            {
              "metric": "ext:cloud.azure.microsoft_datafactory.factories.integrationruntimecpupercentage",
              "aggregation": "AVG",
              "percentile": null,
              "type": "LINE",
              "entityType": "IOT",
              "dimensions": [
                {
                  "id": "0",
                  "name": "dt.entity.custom_device",
                  "values": [],
                  "entityDimension": true
                }
              ],
              "sortAscending": false,
              "sortColumn": true,
              "aggregationRate": "TOTAL"
            }
          ],
          "resultMetadata": {}
        },
        "filtersPerEntityType": {}
      }
    },
    {
      "name": "Custom chart",
      "tileType": "CUSTOM_CHARTING",
      "configured": true,
      "bounds": {
        "top": 342,
        "left": 646,
        "width": 304,
        "height": 304
      },
      "tileFilter": {
        "timeframe": null,
        "managementZone": null
      },
      "filterConfig": {
        "type": "MIXED",
        "customName": "Integration runtime available memory",
        "defaultName": "Custom chart",
        "chartConfig": {
          "legendShown": true,
          "type": "TIMESERIES",
          "series": [
            {
              "metric": "ext:cloud.azure.microsoft_datafactory.factories.integrationruntimeavailablememory",
              "aggregation": "AVG",
              "percentile": null,
              "type": "LINE",
              "entityType": "IOT",
              "dimensions": [
                {
                  "id": "0",
                  "name": "dt.entity.custom_device",
                  "values": [],
                  "entityDimension": true
                }
              ],
              "sortAscending": false,
              "sortColumn": true,
              "aggregationRate": "TOTAL"
            }
          ],
          "resultMetadata": {}
        },
        "filtersPerEntityType": {}
      }
    },
    {
      "name": "Custom chart",
      "tileType": "CUSTOM_CHARTING",
      "configured": true,
      "bounds": {
        "top": 38,
        "left": 988,
        "width": 304,
        "height": 304
      },
      "tileFilter": {
        "timeframe": null,
        "managementZone": null
      },
      "filterConfig": {
        "type": "MIXED",
        "customName": "Failed pipeline runs metrics",
        "defaultName": "Custom chart",
        "chartConfig": {
          "legendShown": true,
          "type": "TOP_LIST",
          "series": [
            {
              "metric": "ext:cloud.azure.microsoft_datafactory.factories.pipelinefailedruns",
              "aggregation": "SUM",
              "percentile": null,
              "type": "LINE",
              "entityType": "IOT",
              "dimensions": [
                {
                  "id": "0",
                  "name": "dt.entity.custom_device",
                  "values": [],
                  "entityDimension": true
                }
              ],
              "sortAscending": false,
              "sortColumn": true,
              "aggregationRate": "TOTAL"
            }
          ],
          "resultMetadata": {}
        },
        "filtersPerEntityType": {}
      }
    },
    {
      "name": "Failures",
      "tileType": "HEADER",
      "configured": true,
      "bounds": {
        "top": 0,
        "left": 988,
        "width": 304,
        "height": 38
      },
      "tileFilter": {
        "timeframe": null,
        "managementZone": null
      }
    },
    {
      "name": "Performance",
      "tileType": "HEADER",
      "configured": true,
      "bounds": {
        "top": 0,
        "left": 646,
        "width": 304,
        "height": 38
      },
      "tileFilter": {
        "timeframe": null,
        "managementZone": null
      }
    },
    {
      "name": "Custom chart",
      "tileType": "CUSTOM_CHARTING",
      "configured": true,
      "bounds": {
        "top": 342,
        "left": 988,
        "width": 304,
        "height": 304
      },
      "tileFilter": {
        "timeframe": null,
        "managementZone": null
      },
      "filterConfig": {
        "type": "MIXED",
        "customName": "Failed activity runs metrics",
        "defaultName": "Custom chart",
        "chartConfig": {
          "legendShown": true,
          "type": "TOP_LIST",
          "series": [
            {
              "metric": "ext:cloud.azure.microsoft_datafactory.factories.activityfailedruns",
              "aggregation": "SUM",
              "percentile": null,
              "type": "LINE",
              "entityType": "IOT",
              "dimensions": [
                {
                  "id": "0",
                  "name": "dt.entity.custom_device",
                  "values": [],
                  "entityDimension": true
                }
              ],
              "sortAscending": false,
              "sortColumn": true,
              "aggregationRate": "TOTAL"
            }
          ],
          "resultMetadata": {}
        },
        "filtersPerEntityType": {}
      }
    },
    {
      "name": "Custom chart",
      "tileType": "CUSTOM_CHARTING",
      "configured": true,
      "bounds": {
        "top": 646,
        "left": 988,
        "width": 304,
        "height": 304
      },
      "tileFilter": {
        "timeframe": null,
        "managementZone": null
      },
      "filterConfig": {
        "type": "MIXED",
        "customName": "Failed trigger runs metrics",
        "defaultName": "Custom chart",
        "chartConfig": {
          "legendShown": true,
          "type": "TOP_LIST",
          "series": [
            {
              "metric": "ext:cloud.azure.microsoft_datafactory.factories.triggerfailedruns",
              "aggregation": "SUM",
              "percentile": null,
              "type": "LINE",
              "entityType": "IOT",
              "dimensions": [
                {
                  "id": "0",
                  "name": "dt.entity.custom_device",
                  "values": [],
                  "entityDimension": true
                }
              ],
              "sortAscending": false,
              "sortColumn": true,
              "aggregationRate": "TOTAL"
            }
          ],
          "resultMetadata": {}
        },
        "filtersPerEntityType": {}
      }
    }
  ]
}